odoo/addons/base_custom_filter/README.rst
odoo/addons/base_custom_filter/__init__.py
odoo/addons/base_custom_filter/__manifest__.py
odoo/addons/base_custom_filter/i18n/base_custom_filter.pot
odoo/addons/base_custom_filter/i18n/es.po
odoo/addons/base_custom_filter/i18n/fr.po
odoo/addons/base_custom_filter/i18n/it.po
odoo/addons/base_custom_filter/models/__init__.py
odoo/addons/base_custom_filter/models/base.py
odoo/addons/base_custom_filter/models/ir_filters.py
odoo/addons/base_custom_filter/models/ir_filters_group.py
odoo/addons/base_custom_filter/readme/CONFIGURE.rst
odoo/addons/base_custom_filter/readme/CONTRIBUTORS.rst
odoo/addons/base_custom_filter/readme/DESCRIPTION.rst
odoo/addons/base_custom_filter/readme/USAGE.rst
odoo/addons/base_custom_filter/security/ir.model.access.csv
odoo/addons/base_custom_filter/static/description/icon.png
odoo/addons/base_custom_filter/static/description/index.html
odoo/addons/base_custom_filter/tests/__init__.py
odoo/addons/base_custom_filter/tests/test_filters.py
odoo/addons/base_custom_filter/views/ir_filters_group_views.xml
odoo/addons/base_custom_filter/views/ir_filters_views.xml
odoo14_addon_base_custom_filter-14.0.1.0.1.dist-info/METADATA
odoo14_addon_base_custom_filter-14.0.1.0.1.dist-info/WHEEL
odoo14_addon_base_custom_filter-14.0.1.0.1.dist-info/top_level.txt
odoo14_addon_base_custom_filter-14.0.1.0.1.dist-info/RECORD
